graylog_json_formatter.py
graylog_json_formatter-1.0.1.dist-info/DESCRIPTION.rst
graylog_json_formatter-1.0.1.dist-info/METADATA
graylog_json_formatter-1.0.1.dist-info/RECORD
graylog_json_formatter-1.0.1.dist-info/WHEEL
graylog_json_formatter-1.0.1.dist-info/metadata.json
graylog_json_formatter-1.0.1.dist-info/top_level.txt
