Metadata-Version: 2.0
Name: graylog-json-formatter
Version: 1.0.1
Summary: JSON formatter for graylog JSON extractor.
Home-page: https://github.com/NewVadim/graylog-json-formatter
Author: Shakurov Vadim Vladimirovich
Author-email: apelsinsd@gmail.com
License: GNU General Public License v3 (GPLv3)
Keywords: graylog json
Platform: UNKNOWN
Classifier: Intended Audience :: Developers
Classifier: License :: OSI Approved :: GNU General Public License v3 (GPLv3)
Classifier: Operating System :: OS Independent
Classifier: Programming Language :: Python
Classifier: Programming Language :: Python :: 2.7
Classifier: Programming Language :: Python :: 3.3
Classifier: Programming Language :: Python :: 3.4
Classifier: Programming Language :: Python :: 3.5
Classifier: Programming Language :: Python :: 3.6
Classifier: Programming Language :: Python :: 3.7
Classifier: Programming Language :: Python :: 3.8
